auth_utils/__init__.py
auth_utils/backends.py
auth_utils/django18_compat.py
auth_utils/views.py
auth_utils/templatetags/__init__.py
auth_utils/templatetags/auth_utils.py
django_auth_utils-0.1.1.dist-info/DESCRIPTION.rst
django_auth_utils-0.1.1.dist-info/METADATA
django_auth_utils-0.1.1.dist-info/RECORD
django_auth_utils-0.1.1.dist-info/WHEEL
django_auth_utils-0.1.1.dist-info/metadata.json
django_auth_utils-0.1.1.dist-info/top_level.txt
