Metadata-Version: 2.0
Name: django-auth-utils
Version: 0.1.1
Summary: Django authentication and authorization utilities
Home-page: https://github.com/pjdelport/django-auth-utils
Author: Pi Delport
Author-email: pjdelport@gmail.com
License: Public Domain
Platform: UNKNOWN
Classifier: Development Status :: 3 - Alpha
Classifier: Environment :: Web Environment
Classifier: Framework :: Django
Classifier: Intended Audience :: Developers
Classifier: License :: Public Domain
Classifier: Programming Language :: Python :: 2
Classifier: Programming Language :: Python :: 3
Classifier: Topic :: Internet :: WWW/HTTP
Classifier: Topic :: Security
Classifier: Topic :: Software Development :: Libraries
Classifier: Topic :: Utilities
Requires-Dist: attrs
Requires-Dist: Django
